Workbook

Sheet Leia-me
A1: Base consolidada — necessidade de fertilizantes (posição 16/10/2026)
A2: Origem: Necessidade Fertilizante OUT 2026.xlsx — abas LOC. 1.000ha (cenário A) e LOC. 450ha (cenário B). Nenhum valor da origem foi alterado.
A4: Abas
A5: Premissas | B5: Dados copiados da planilha de origem, com a célula de onde vieram (texto azul).
A6: Balanço | B6: Toda a conta da necessidade, do saldo e da compra, em fórmulas; colunas F:I conferem com a origem.
A7: Estoque | B7: Estoque por fórmula em 16/10/2026 e área equivalente (estoque ÷ dose implícita da origem).
A8: Curva_16-00-20 | B8: Necessidade acumulada × disponível, com a premissa ilustrativa de aplicação uniforme até o término da safra.
A9: Sensibilidade | B9: Dias de vinhaça com K, variação de demanda e preços: células amarelas são editáveis.
A10: Indicadores | B10: Painel de acompanhamento: o que já é mensurável e o que depende de dado.
A11: Inconsistências | B11: Pontos da planilha de origem que precisam de correção ou complemento.
A12: Conferência | B12: 87 conferências: fórmulas e totais da origem refeitos em Python e comparados com o valor gravado pelo Excel, mais a checagem da sensibilidade.
A14: Legenda
A15: Texto azul | B15: dado copiado da planilha de origem (ver coluna Origem)
A16: Texto preto | B16: fórmula
A17: Texto verde | B17: ligação simples a outra aba
A18: Fundo amarelo | B18: premissa que o usuário pode alterar (aba Sensibilidade)
A20: Premissas desta base
A21: Cenários | B21: Os cenários A e B são as duas abas da planilha de origem; só muda o número de dias de vinhaça com K adequado (C13).
A22: Localizada CRV | B22: Calculada como MÁXIMO(0; área de localizada estimada − Cargill a adubar). Reproduz a aba A (=C14−H36) e o 0 digitado em H38 da aba B.
A23: Nutrientes | B23: Pela garantia expressa no nome da fórmula (N-P2O5-K2O, em %). O teor de K da vinhaça não está na origem e não foi estimado.
A24: Curva | B24: Distribuição uniforme da necessidade entre a data-base e o término da safra — ilustrativa; a origem não traz demanda mensal nem datas de entrega.
A25: Preços | B25: A origem não traz preços; nenhum preço foi assumido. Informe-os na aba Sensibilidade.

Sheet Premissas
A1: Premissas copiadas da planilha de origem
A2: Texto azul = valor da origem. Altere aqui só se a origem mudar.
A4: Item | B4: Unidade | C4: Cenário A (LOC. 1.000ha) | D4: Cenário B (LOC. 450ha) | E4: Origem (célula nas duas abas)
A5: Data-base | B5: data | C5: 46311 | D5: 46311 | E5: A10
A6: Data limite da vinhaça localizada | B6: data | C6: 46356 | D6: 46356 | E6: B10
A7: Término da safra | B7: data | C7: 46371 | D7: 46371 | E7: C10
A8: Ritmo da vinhaça localizada (média de setembro) | B8: ha/dia | C8: 50.78 | D8: 50.78 | E8: C12
A9: Dias com vinhaça de K adequado | B9: dias | C9: 20 | D9: 0 | E9: C13
A10: Área de tratos da Cargill | B10: ha | C10: 1200 | D10: 1200 | E10: E36 (H36 usa 1.200 digitado)
A11: Realizado Cargill (vinhaça localizada) | B11: ha | C11: 753.37 | D11: 753.37 | E11: F36 = B20
A12: Área à colher CRV — parcela 1 | B12: ha | C12: 11593 | D12: 11593 | E12: D38 (=11593+9354+8779)
A13: Área à colher CRV — parcela 2 | B13: ha | C13: 9354 | D13: 9354 | E13: D38
A14: Área à colher CRV — parcela 3 | B14: ha | C14: 8779 | D14: 8779 | E14: D38
A15: Plantio (renovação) excluído dos tratos | B15: ha | C15: 1000 | D15: 1000 | E15: C38
A16: Realizado CRV — vinhaça localizada | B16: ha | C16: 5795.19 | D16: 5795.19 | E16: B22 = F38
... A30: Plantio projetado — renovação | B30: ha | C30: 1000 | D30: 1000 | E30: nota A42

Sheet Balanço
A1: Balanço de necessidade, disponibilidade e compra
A2: Colunas C:D em fórmulas; F:G trazem o valor gravado na planilha de origem; H:I devem ser zero.
A4: Item | B4: Unidade | C4: Cenário A | D4: Cenário B | E4: Conta | F4: Planilha A | G4: Planilha B | H4: Dif. A | I4: Dif. B | J4: Célula na origem
A5: Dias até o limite da localizada | B5: dias | C5: =Premissas!C6-Premissas!C5 -> 45 | D5: =Premissas!D6-Premissas!D5 -> 45 | E5: Data limite da vinhaça localizada − Data − base | F5: 45 | G5: 45 | H5: =ROUND(C5-F5,6) -> 0 | I5: =ROUND(D5-G5,6) -> 0 | J5: B11
A6: Dias até o término da safra | B6: dias | C6: =Premissas!C7-Premissas!C5 -> 60 | D6: =Premissas!D7-Premissas!D5 -> 60 | E6: Término da safra − Data − base | F6: 60 | G6: 60 | H6: =ROUND(C6-F6,6) -> 0 | I6: =ROUND(D6-G6,6) -> 0 | J6: C11
A7: Área de localizada estimada | B7: ha | C7: =Premissas!C9*Premissas!C8 -> 1015.6 | D7: =Premissas!D9*Premissas!D8 -> 0 | E7: Dias com vinhaça de K adequado × Ritmo da vinhaça localizada (média de setembro) | F7: 1015.6 | G7: 0 | H7: =ROUND(C7-F7,6) -> 0 | I7: =ROUND(D7-G7,6) -> 0 | J7: C14
A8: Cargill a adubar | B8: ha | C8: =Premissas!C10-Premissas!C11 -> 446.63 | D8: =Premissas!D10-Premissas!D11 -> 446.63 | E8: Área de tratos da Cargill − Realizado Cargill (vinhaça localizada) | F8: 446.63 | G8: 446.63 | H8: =ROUND(C8-F8,6) -> 0 | I8: =ROUND(D8-G8,6) -> 0 | J8: H36
A9: Área à colher CRV | B9: ha | C9: =Premissas!C12+Premissas!C13+Premissas!C14 -> 29726 | D9: =Premissas!D12+Premissas!D13+Premissas!D14 -> 29726 | E9: Área à colher CRV — parcela 1 + Área à colher CRV — parcela 2 + Área à colher CRV — parcela 3 | F9: 29726 | G9: 29726 | H9: =ROUND(C9-F9,6) -> 0 | I9: =ROUND(D9-G9,6) -> 0 | J9: D38
A10: Área de tratos CRV | B10: ha | C10: =C9-Premissas!C15 -> 28726 | D10: =D9-Premissas!D15 -> 28726 | E10: Área à colher CRV − Plantio (renovação) excluído dos tratos | F10: 28726 | G10: 28726 | H10: =ROUND(C10-F10,6) -> 0 | I10: =ROUND(D10-G10,6) -> 0 | J10: E38
A11: Realizado CRV | B11: ha | C11: =Premissas!C16+Premissas!C17 -> 14236.43 | D11: =Premissas!D16+Premissas!D17 -> 14236.43 | E11: Realizado CRV — vinhaça localizada + Realizado CRV — fertilizante mineral | F11: 14236.43 | G11: 14236.43 | H11: =ROUND(C11-F11,6) -> 0 | I11: =ROUND(D11-G11,6) -> 0 | J11: F40
A12: Localizada CRV a adubar | B12: ha | C12: =MAX(0,C7-C8) -> 568.97 | D12: =MAX(0,D7-D8) -> 0 | E12: máximo(0; Área de localizada estimada − Cargill a adubar) | F12: 568.97 | G12: 0 | H12: =ROUND(C12-F12,6) -> 0 | I12: =ROUND(D12-G12,6) -> 0 | J12: H38
A13: Fertilizante mineral CRV a adubar | B13: ha | C13: =C10-C11-C12-Premissas!C18 -> 10843.67 | D13: =D10-D11-D12-Premissas!D18 -> 11412.64 | E13: Área de tratos CRV − Realizado CRV − Localizada CRV a adubar − Cana bisada — área | F13: 10843.67 | G13: 11412.64 | H13: =ROUND(C13-F13,6) -> 0 | I13: =ROUND(D13-G13,6) -> 0 | J13: H39
A14: Total a adubar | B14: ha | C14: =C12+C13+C8 -> 11859.27 | D14: =D12+D13+D8 -> 11859.27 | E14: Localizada CRV a adubar + Fertilizante mineral CRV a adubar + Cargill a adubar | F14: 11859.27 | G14: 11859.27 | H14: =ROUND(C14-F14,6) -> 0 | I14: =ROUND(D14-G14,6) -> 0 | J14: H40
A15: Necessidade de 46-00-00 | B15: t | C15: =Premissas!C20*C12/1000 -> 113.794 | D15: =Premissas!D20*D12/1000 -> 0 | E15: Dose média 46 − 00 − 00 × Localizada CRV a adubar ÷ 1000 | F15: 113.794 | G15: 0 | H15: =ROUND(C15-F15,6) -> 0 | I15: =ROUND(D15-G15,6) -> 0 | J15: K38 = B50
A16: Necessidade de 16-00-20 | B16: t | C16: =Premissas!C21*C13/1000 -> 5421.835 | D16: =Premissas!D21*D13/1000 -> 5706.32 | E16: Dose média 16 − 00 − 20 × Fertilizante mineral CRV a adubar ÷ 1000 | F16: 5421.835 | G16: 5706.32 | H16: =ROUND(C16-F16,6) -> 0 | I16: =ROUND(D16-G16,6) -> 0 | J16: K39 = B51
A17: Necessidade total | B17: t | C17: =C15+C16 -> 5535.629 | D17: =D15+D16 -> 5706.32 | E17: Necessidade de 46 − 00 − 00 + Necessidade de 16 − 00 − 20
A18: Disponível 46-00-00 (estoque + a receber) | B18: t | C18: =Premissas!C22+Premissas!C24 -> 1506.97 | D18: =Premissas!D22+Premissas!D24 -> 1506.97 | E18: Estoque 46 − 00 − 00 (CRV − MG) + Comprado a receber 46 − 00 − 00 | F18: 1506.97 | G18: 1506.97 | H18: =ROUND(C18-F18,6) -> 0 | I18: =ROUND(D18-G18,6) -> 0 | J18: E50
A19: Disponível 16-00-20 (estoque + a receber) | B19: t | C19: =Premissas!C23+Premissas!C25 -> 3162 | D19: =Premissas!D23+Premissas!D25 -> 3162 | E19: Estoque 16 − 00 − 20 (CRV − MG) + Comprado a receber 16 − 00 − 20 | F19: 3162 | G19: 3162 | H19: =ROUND(C19-F19,6) -> 0 | I19: =ROUND(D19-G19,6) -> 0 | J19: E51
A20: Saldo 46-00-00 (disponível − necessidade) | B20: t | C20: =C18-C15 -> 1393.176 | D20: =D18-D15 -> 1506.97 | E20: Disponível 46 − 00 − 00 (estoque + a receber) − Necessidade de 46 − 00 − 00 | F20: 1393.176 | G20: 1506.97 | H20: =ROUND(C20-F20,6) -> 0 | I20: =ROUND(D20-G20,6) -> 0 | J20: F50
A21: Saldo 16-00-20 (disponível − necessidade) | B21: t | C21: =C19-C16 -> -2259.835 | D21: =D19-D16 -> -2544.32 | E21: Disponível 16 − 00 − 20 (estoque + a receber) − Necessidade de 16 − 00 − 20 | F21: -2259.835 | G21: -2544.32 | H21: =ROUND(C21-F21,6) -> 0 | I21: =ROUND(D21-G21,6) -> 0 | J21: F51
A22: Compra necessária de 16-00-20 | B22: t | C22: =MAX(0,-C21) -> 2259.835 | D22: =MAX(0,-D21) -> 2544.32 | E22: máximo(0; − Saldo 16 − 00 − 20 (disponível − necessidade)) | F22: 2259.835 | G22: 2544.32 | H22: =ROUND(C22-F22,6) -> 0 | I22: =ROUND(D22-G22,6) -> 0 | J22: B56
A23: Cobertura do 16-00-20 só com estoque | B23: % | C23: =Premissas!C23/C16 -> 0.2087854 | D23: =Premissas!D23/D16 -> 0.19837654 | E23: Estoque 16 − 00 − 20 (CRV − MG) ÷ Necessidade de 16 − 00 − 20
A24: Cobertura do 16-00-20 com estoque + a receber | B24: % | C24: =C19/C16 -> 0.58319739 | D24: =D19/D16 -> 0.55412245 | E24: Disponível 16 − 00 − 20 (estoque + a receber) ÷ Necessidade de 16 − 00 − 20
A25: Participação do 16-00-20 na necessidade | B25: % | C25: =C16/C17 -> 0.97944335 | D25: =D16/D17 -> 1 | E25: Necessidade de 16 − 00 − 20 ÷ Necessidade total
A26: N contido na necessidade | B26: t | C26: =C16*Premissas!C26+C15*Premissas!C28 -> 919.83884 | D26: =D16*Premissas!D26+D15*Premissas!D28 -> 913.0112 | E26: Necessidade de 16 − 00 − 20 × Teor de N do 16 − 00 − 20 + Necessidade de 46 − 00 − 00 × Teor de N do 46 − 00 − 00
A27: K2O contido na necessidade (só 16-00-20) | B27: t | C27: =C16*Premissas!C27 -> 1084.367 | D27: =D16*Premissas!D27 -> 1141.264 | E27: Necessidade de 16 − 00 − 20 × Teor de K2O do 16 − 00 − 20
A28: N contido no excedente de 46-00-00 | B28: t | C28: =MAX(0,C20)*Premissas!C28 -> 640.86096 | D28: =MAX(0,D20)*Premissas!D28 -> 693.2062 | E28: máximo(0; Saldo 46 − 00 − 00 (disponível − necessidade)) × Teor de N do 46 − 00 − 00
A29: N do déficit de 16-00-20 | B29: t | C29: =C22*Premissas!C26 -> 361.5736 | D29: =D22*Premissas!D26 -> 407.0912 | E29: Compra necessária de 16 − 00 − 20 × Teor de N do 16 − 00 − 20
A30: K2O do déficit de 16-00-20 | B30: t | C30: =C22*Premissas!C27 -> 451.967 | D30: =D22*Premissas!D27 -> 508.864 | E30: Compra necessária de 16 − 00 − 20 × Teor de K2O do 16 − 00 − 20
A31: Área de tratos total (CRV + Cargill) | B31: ha | C31: =C10+Premissas!C10 -> 29926 | D31: =D10+Premissas!D10 -> 29926 | E31: Área de tratos CRV + Área de tratos da Cargill | J31: E40
A32: Área já adubada (CRV + Cargill) | B32: ha | C32: =C11+Premissas!C11 -> 14989.8 | D32: =D11+Premissas!D11 -> 14989.8 | E32: Realizado CRV + Realizado Cargill (vinhaça localizada)
A33: Área já adubada / área de tratos | B33: % | C33: =C32/C31 -> 0.50089554 | D33: =D32/D31 -> 0.50089554 | E33: Área já adubada (CRV + Cargill) ÷ Área de tratos total (CRV + Cargill)
A34: Cana bisada (t) | B34: t | C34: =Premissas!C18*Premissas!C19 -> 200000.45 | D34: =Premissas!D18*Premissas!D19 -> 200000.45 | E34: Cana bisada — área × Cana bisada — TCH estimado | F34: 200000.45 | G34: 200000.45 | H34: =ROUND(C34-F34,6) -> 0 | I34: =ROUND(D34-G34,6) -> 0 | J34: C45
A35: Ritmo médio para adubar o restante até o término (referência) | B35: ha/dia | C35: =C14/C6 -> 197.6545 | D35: =D14/D6 -> 197.6545 | E35: Total a adubar ÷ Dias até o término da safra
A36: Consumo diário de 16-00-20 (premissa linear) | B36: t/dia | C36: =C16/C6 -> 90.363917 | D36: =D16/D6 -> 95.105333 | E36: Necessidade de 16 − 00 − 20 ÷ Dias até o término da safra
A37: Dias de cobertura do estoque de 16-00-20 | B37: dias | C37: =Premissas!C23/C36 -> 12.527124 | D37: =Premissas!D23/D36 -> 11.902592 | E37: Estoque 16 − 00 − 20 (CRV − MG) ÷ Consumo diário de 16 − 00 − 20 (premissa linear)
A38: Dias de cobertura do disponível de 16-00-20 | B38: dias | C38: =C19/C36 -> 34.991843 | D38: =D19/D36 -> 33.247347 | E38: Disponível 16 − 00 − 20 (estoque + a receber) ÷ Consumo diário de 16 − 00 − 20 (premissa linear)
A39: Esgotamento do estoque de 16-00-20 (premissa linear) | B39: data | C39: =Premissas!C5+C37 -> 46323.527 | D39: =Premissas!D5+D37 -> 46322.903 | E39: Data − base + Dias de cobertura do estoque de 16 − 00 − 20
A40: Esgotamento do disponível de 16-00-20 (premissa linear) | B40: data | C40: =Premissas!C5+C38 -> 46345.992 | D40: =Premissas!D5+D38 -> 46344.247 | E40: Data − base + Dias de cobertura do disponível de 16 − 00 − 20
A42: Conferência geral (soma das diferenças absolutas) | H42: =SUMPRODUCT(ABS(H5:I40)) -> 0

Sheet Estoque
A1: Estoque de fertilizantes em 16/10/2026
A2: Área equivalente = estoque ÷ dose implícita usada na própria planilha (quadro I47:K61).
A4: Fórmula | B4: Grupo | C4: Estoque (t) | D4: Dose implícita (t/ha) | E4: Área equivalente (ha) | F4: Origem
A5: 16-00-20 | B5: Socaria | C5: 1132 | D5: 0.5 | E5: =C5/D5 -> 2264 | F5: I49:K49
A6: 46-00-00 | B6: Socaria | C6: 356.97 | D6: 0.2 | E6: =C6/D6 -> 1784.85 | F6: I50:K50
A7: 21-00-00 | B7: Socaria | C7: 126 | D7: 0.4 | E7: =C7/D7 -> 315 | F7: I51:K51
A8: 25-00-00 | B8: Socaria | C8: 0.85 | D8: 0.4 | E8: =C8/D8 -> 2.125 | F8: I52:K52
A9: 13-00-34 | B9: Socaria | C9: 4 | D9: 0.5 | E9: =C9/D9 -> 8 | F9: I53:K53
A10: 06-26-25 | B10: Plantio | C10: 689.5 | D10: 0.6 | E10: =C10/D10 -> 1149.1667 | F10: I54:K54
A11: 06-30-25 | B11: Plantio | C11: 139.86 | D11: 0.6 | E11: =C11/D11 -> 233.1 | F11: I55:K55
A12: 06-27-24 | B12: Plantio | C12: 6 | D12: 0.6 | E12: =C12/D12 -> 10 | F12: I56:K56
A13: 05-25-25 | B13: Plantio | C13: 2.95 | D13: 0.6 | E13: =C13/D13 -> 4.9166667 | F13: I57:K57
A14: Oxyfertil | B14: Não classificado | C14: 142.19 | D14: 0.5 | E14: =C14/D14 -> 284.38 | F14: I58:K58
A16: Subtotal Socaria | C16: =SUMIF($B$5:$B$14,"Socaria",C$5:C$14) -> 1619.82 | E16: =SUMIF($B$5:$B$14,"Socaria",E$5:E$14) -> 4373.975
A17: Subtotal Plantio | C17: =SUMIF($B$5:$B$14,"Plantio",C$5:C$14) -> 838.31 | E17: =SUMIF($B$5:$B$14,"Plantio",E$5:E$14) -> 1397.1833
A18: Subtotal Não classificado | C18: =SUMIF($B$5:$B$14,"Não classificado",C$5:C$14) -> 142.19 | E18: =SUMIF($B$5:$B$14,"Não classificado",E$5:E$14) -> 284.38
A19: Total | C19: =SUM(C5:C14) -> 2600.32
A20: A origem soma K49:K53 em SOCARIA e K54:K57 em PLANTIO; o Oxyfertil (linha 58) fica fora dos dois.
A21: As áreas não se somam entre produtos: o 46-00-00 só substitui o 16-00-20 onde há vinhaça localizada (K).

Sheet Curva_16-00-20
A1: Curva de abastecimento do 16-00-20
A2: Premissa ilustrativa: necessidade distribuída por igual entre a data-base e o término da safra.
A4: Dia | B4: Data | C4: Necessidade acumulada A (t) | D4: Estoque A (t) | E4: Estoque + a receber A (t) | F4: Necessidade acumulada B (t) | G4: Estoque B (t) | H4: Estoque + a receber B (t)
A5: 0 | B5: =Premissas!$C$5+A5 -> 46311 | C5: =Balanço!$C$36*A5 -> 0 | D5: =Premissas!$C$23 -> 1132 | E5: =Balanço!$C$19 -> 3162 | F5: =Balanço!$D$36*A5 -> 0 | G5: =Premissas!$D$23 -> 1132 | H5: =Balanço!$D$19 -> 3162
A6: 5 | B6: =Premissas!$C$5+A6 -> 46316 | C6: =Balanço!$C$36*A6 -> 451.81958 | D6: =Premissas!$C$23 -> 1132 | E6: =Balanço!$C$19 -> 3162 | F6: =Balanço!$D$36*A6 -> 475.52667 | G6: =Premissas!$D$23 -> 1132 | H6: =Balanço!$D$19 -> 3162
A7: 10 | B7: =Premissas!$C$5+A7 -> 46321 | C7: =Balanço!$C$36*A7 -> 903.63917 | D7: =Premissas!$C$23 -> 1132 | E7: =Balanço!$C$19 -> 3162 | F7: =Balanço!$D$36*A7 -> 951.05333 | G7: =Premissas!$D$23 -> 1132 | H7: =Balanço!$D$19 -> 3162
A8: 15 | B8: =Premissas!$C$5+A8 -> 46326 | C8: =Balanço!$C$36*A8 -> 1355.4588 | D8: =Premissas!$C$23 -> 1132 | E8: =Balanço!$C$19 -> 3162 | F8: =Balanço!$D$36*A8 -> 1426.58 | G8: =Premissas!$D$23 -> 1132 | H8: =Balanço!$D$19 -> 3162
A9: 20 | B9: =Premissas!$C$5+A9 -> 46331 | C9: =Balanço!$C$36*A9 -> 1807.2783 | D9: =Premissas!$C$23 -> 1132 | E9: =Balanço!$C$19 -> 3162 | F9: =Balanço!$D$36*A9 -> 1902.1067 | G9: =Premissas!$D$23 -> 1132 | H9: =Balanço!$D$19 -> 3162
A10: 25 | B10: =Premissas!$C$5+A10 -> 46336 | C10: =Balanço!$C$36*A10 -> 2259.0979 | D10: =Premissas!$C$23 -> 1132 | E10: =Balanço!$C$19 -> 3162 | F10: =Balanço!$D$36*A10 -> 2377.6333 | G10: =Premissas!$D$23 -> 1132 | H10: =Balanço!$D$19 -> 3162
A11: 30 | B11: =Premissas!$C$5+A11 -> 46341 | C11: =Balanço!$C$36*A11 -> 2710.9175 | D11: =Premissas!$C$23 -> 1132 | E11: =Balanço!$C$19 -> 3162 | F11: =Balanço!$D$36*A11 -> 2853.16 | G11: =Premissas!$D$23 -> 1132 | H11: =Balanço!$D$19 -> 3162
A12: 35 | B12: =Premissas!$C$5+A12 -> 46346 | C12: =Balanço!$C$36*A12 -> 3162.7371 | D12: =Premissas!$C$23 -> 1132 | E12: =Balanço!$C$19 -> 3162 | F12: =Balanço!$D$36*A12 -> 3328.6867 | G12: =Premissas!$D$23 -> 1132 | H12: =Balanço!$D$19 -> 3162
A13: 40 | B13: =Premissas!$C$5+A13 -> 46351 | C13: =Balanço!$C$36*A13 -> 3614.5567 | D13: =Premissas!$C$23 -> 1132 | E13: =Balanço!$C$19 -> 3162 | F13: =Balanço!$D$36*A13 -> 3804.2133 | G13: =Premissas!$D$23 -> 1132 | H13: =Balanço!$D$19 -> 3162
A14: 45 | B14: =Premissas!$C$5+A14 -> 46356 | C14: =Balanço!$C$36*A14 -> 4066.3763 | D14: =Premissas!$C$23 -> 1132 | E14: =Balanço!$C$19 -> 3162 | F14: =Balanço!$D$36*A14 -> 4279.74 | G14: =Premissas!$D$23 -> 1132 | H14: =Balanço!$D$19 -> 3162
A15: 50 | B15: =Premissas!$C$5+A15 -> 46361 | C15: =Balanço!$C$36*A15 -> 4518.1958 | D15: =Premissas!$C$23 -> 1132 | E15: =Balanço!$C$19 -> 3162 | F15: =Balanço!$D$36*A15 -> 4755.2667 | G15: =Premissas!$D$23 -> 1132 | H15: =Balanço!$D$19 -> 3162
A16: 55 | B16: =Premissas!$C$5+A16 -> 46366 | C16: =Balanço!$C$36*A16 -> 4970.0154 | D16: =Premissas!$C$23 -> 1132 | E16: =Balanço!$C$19 -> 3162 | F16: =Balanço!$D$36*A16 -> 5230.7933 | G16: =Premissas!$D$23 -> 1132 | H16: =Balanço!$D$19 -> 3162
A17: 60 | B17: =Premissas!$C$5+A17 -> 46371 | C17: =Balanço!$C$36*A17 -> 5421.835 | D17: =Premissas!$C$23 -> 1132 | E17: =Balanço!$C$19 -> 3162 | F17: =Balanço!$D$36*A17 -> 5706.32 | G17: =Premissas!$D$23 -> 1132 | H17: =Balanço!$D$19 -> 3162

Sheet Sensibilidade
A1: Sensibilidade e cenários definidos pelo usuário
A2: Células amarelas são editáveis. Nada aqui é previsão oficial da usina.
A4: 1. Dias de vinhaça localizada com K adequado (mesma lógica da aba A da origem)
A5: Dias (editável) | B5: Localizada CRV (ha) | C5: Mineral CRV (ha) | D5: Necessidade 16-00-20 (t) | E5: Necessidade 46-00-00 (t) | F5: Compra 16-00-20 (t) | G5: Excedente 46-00-00 (t)
A6: 0 | B6: =MAX(0,A6*Premissas!$C$8-Balanço!$C$8) -> 0 | C6: =Balanço!$C$10-Balanço!$C$11-Premissas!$C$18-B6 -> 11412.64 | D6: =C6*Premissas!$C$21/1000 -> 5706.32 | E6: =B6*Premissas!$C$20/1000 -> 0 | F6: =MAX(0,D6-Balanço!$C$19) -> 2544.32 | G6: =Balanço!$C$18-E6 -> 1506.97
A7: 10 | B7: =MAX(0,A7*Premissas!$C$8-Balanço!$C$8) -> 61.17 | C7: =Balanço!$C$10-Balanço!$C$11-Premissas!$C$18-B7 -> 11351.47 | D7: =C7*Premissas!$C$21/1000 -> 5675.735 | E7: =B7*Premissas!$C$20/1000 -> 12.234 | F7: =MAX(0,D7-Balanço!$C$19) -> 2513.735 | G7: =Balanço!$C$18-E7 -> 1494.736
A8: 20 | B8: =MAX(0,A8*Premissas!$C$8-Balanço!$C$8) -> 568.97 | C8: =Balanço!$C$10-Balanço!$C$11-Premissas!$C$18-B8 -> 10843.67 | D8: =C8*Premissas!$C$21/1000 -> 5421.835 | E8: =B8*Premissas!$C$20/1000 -> 113.794 | F8: =MAX(0,D8-Balanço!$C$19) -> 2259.835 | G8: =Balanço!$C$18-E8 -> 1393.176
A9: 30 | B9: =MAX(0,A9*Premissas!$C$8-Balanço!$C$8) -> 1076.77 | C9: =Balanço!$C$10-Balanço!$C$11-Premissas!$C$18-B9 -> 10335.87 | D9: =C9*Premissas!$C$21/1000 -> 5167.935 | E9: =B9*Premissas!$C$20/1000 -> 215.354 | F9: =MAX(0,D9-Balanço!$C$19) -> 2005.935 | G9: =Balanço!$C$18-E9 -> 1291.616
A10: 45 | B10: =MAX(0,A10*Premissas!$C$8-Balanço!$C$8) -> 1838.47 | C10: =Balanço!$C$10-Balanço!$C$11-Premissas!$C$18-B10 -> 9574.17 | D10: =C10*Premissas!$C$21/1000 -> 4787.085 | E10: =B10*Premissas!$C$20/1000 -> 367.694 | F10: =MAX(0,D10-Balanço!$C$19) -> 1625.085 | G10: =Balanço!$C$18-E10 -> 1139.276
A11: 20 dias reproduz o cenário A e 0 dia o cenário B. Acima de 20 dias, só com vinhaça de K adequado e até a data limite (45 dias).
A13: 2. Variação de demanda definida pelo usuário
A14: Variação sobre a necessidade de 16-00-20 (ex.: 10% ou −5%) | B14: 0
A15: Item | B15: Cenário A | C15: Cenário B
A16: Necessidade de 16-00-20 ajustada (t) | B16: =Balanço!C16*(1+$B$14) -> 5421.835 | C16: =Balanço!D16*(1+$B$14) -> 5706.32
A17: Compra de 16-00-20 ajustada (t) | B17: =MAX(0,B16-Balanço!C19) -> 2259.835 | C17: =MAX(0,C16-Balanço!D19) -> 2544.32
A20: 3. Preços definidos pelo usuário (a origem não traz preços)
A21: Preço do 16-00-20 (R$/t) | C21: ← informe o preço; enquanto vazio, o orçamento mostra "informar preço"
A22: Preço do 46-00-00 (R$/t)
A23: Item | B23: Cenário A | C23: Cenário B
A24: Orçamento da compra de 16-00-20 (R$) | B24: =IF($B$21="","informar preço",Balanço!C22*$B$21) -> informar preço | C24: =IF($B$21="","informar preço",Balanço!D22*$B$21) -> informar preço
A25: Orçamento da compra ajustada pela variação de demanda (R$) | B25: =IF($B$21="","informar preço",B17*$B$21) -> informar preço | C25: =IF($B$21="","informar preço",C17*$B$21) -> informar preço
A26: Custo do 16-00-20 por hectare (R$/ha) | B26: =IF($B$21="","informar preço",$B$21*Premissas!C21/1000) -> informar preço | C26: =IF($B$21="","informar preço",$B$21*Premissas!D21/1000) -> informar preço
A27: Custo do 46-00-00 por hectare (R$/ha) | B27: =IF($B$22="","informar preço",$B$22*Premissas!C20/1000) -> informar preço | C27: =IF($B$22="","informar preço",$B$22*Premissas!D20/1000) -> informar preço
A28: Valor do excedente de 46-00-00 (R$) | B28: =IF($B$22="","informar preço",MAX(0,Balanço!C20)*$B$22) -> informar preço | C28: =IF($B$22="","informar preço",MAX(0,Balanço!D20)*$B$22) -> informar preço
A29: Efeito de cada R$ 100/t no preço do 16-00-20 sobre a compra (R$) | B29: =Balanço!C22*100 -> 225983.5 | C29: =Balanço!D22*100 -> 254432
A30: Efeito de cada R$ 100/t no preço do 46-00-00 sobre o excedente (R$) | B30: =MAX(0,Balanço!C20)*100 -> 139317.6 | C30: =MAX(0,Balanço!D20)*100 -> 150697

Sheet Indicadores
A1: Painel de indicadores de acompanhamento
A2: "pendente" = depende de dado que a planilha de origem não traz.
A4: Indicador | B4: Unidade | C4: Cenário A | D4: Cenário B | E4: Situação | F4: Conta ou dado que falta
A5: Necessidade total prevista | B5: t | C5: =Balanço!C17 -> 5535.629 | D5: =Balanço!D17 -> 5706.32 | E5: mensurável | F5: Balanço: necessidade de 46-00-00 + 16-00-20
A6: Volume comprado a receber | B6: t | C6: =Premissas!C25+Premissas!C24 -> 3180 | D6: =Premissas!D25+Premissas!D24 -> 3180 | E6: mensurável | F6: D50 + D51 da origem (sem datas de entrega)
A7: Volume entregue | B7: t | C7: pendente | D7: pendente | E7: depende de dado | F7: registro de recebimentos por data
A8: Área já adubada | B8: ha | C8: =Balanço!C32 -> 14989.8 | D8: =Balanço!D32 -> 14989.8 | E8: mensurável | F8: toneladas aplicadas só existem para a vinhaça localizada (linhas 27–28)
A9: Saldo a comprar de 16-00-20 | B9: t | C9: =Balanço!C22 -> 2259.835 | D9: =Balanço!D22 -> 2544.32 | E9: mensurável | F9: B56 da origem
A10: Aderência ao cronograma | B10: % | C10: pendente | D10: pendente | E10: depende de dado | F10: cronograma de entrega e de aplicação
A11: Custo previsto × realizado | B11: R$ | C11: pendente | D11: pendente | E11: depende de dado | F11: preços contratados e notas fiscais
A12: Estoque projetado de 46-00-00 no fim da safra | B12: t | C12: =Balanço!C20 -> 1393.176 | D12: =Balanço!D20 -> 1506.97 | E12: mensurável | F12: o 16-00-20 zera depois da compra

Sheet Inconsistências
A1: Inconsistências e dados faltantes na planilha de origem
A2: Nenhuma célula da origem foi alterada; os pontos abaixo pedem validação.
A4: # | B4: Gravidade | C4: Onde | D4: Achado | E4: Efeito
A5: 1 | B5: Alta | C5: Ambas as abas, linhas 26 a 29 | D5: Quadro de vinhaça localizada não fecha: total B26 = 8517.09 ha, mas B27+B28+B29 = 6081.74 ha (diferença 2435.35 ha). B27+B28 = 5328.37 ha também difere de B22 = 5795.19 ha. As linhas 27 a 29 não têm descrição na coluna A. | E5: Não afeta a necessidade restante (calculada pelas áreas da seção 3), mas impede conciliar o consumo realizado por produto.
A6: 2 | B6: Média | C6: LOC. 450ha!H38 | D6: H38 está digitado como 0; na aba A é a fórmula =C14-H36. Com C13 = 0 a fórmula daria -446,63 ha, por isso o valor fixo está certo neste cenário, mas não se atualiza se C13 mudar. | E6: Se alguém alterar os dias de K na aba B, a necessidade não acompanha.
A7: 3 | B7: Baixa | C7: Ambas as abas, H36 | D7: H36 = 1200 - F36 usa 1.200 digitado em vez de referenciar E36. | E7: Risco de divergência se a área de tratos da Cargill mudar.
A8: 4 | B8: Média | C8: Ambas as abas, D38 | D8: Área à colher da CRV = 11.593 + 9.354 + 8.779 ha digitados na fórmula, sem identificar a que corresponde cada parcela. | E8: Sem rastreabilidade por bloco/fazenda; impede a visão de necessidade por área produtiva.
A9: 5 | B9: Média | C9: Ambas as abas, K58 × K60/K61 | D9: Oxyfertil (142,19 t; 284,38 ha equivalentes) não entra no subtotal SOCARIA nem no PLANTIO. | E9: Estoque sem destino definido; pode reduzir compra se tiver uso agronômico validado.
A10: 6 | B10: Baixa | C10: Colunas C, I e A dos quadros | D10: A mesma fórmula aparece como '16-00-20.' e '16-00-20' (e '46-00-00.' e '46-00-00'). | E10: Quebra PROCV/tabela dinâmica que consolidem por produto.
A11: 7 | B11: Média | C11: Ambas as abas, quadro de estoque (I47:K58) | D11: 21-00-00 (126 t), 13-00-34 (4 t), 25-00-00 (0,85 t) e Oxyfertil (142,19 t) estão em estoque mas fora do balanço de necessidade (B50:F51). | E11: O saldo a comprar considera só 16-00-20 e 46-00-00.
A12: 8 | B12: Média | C12: Ambas as abas, A42 | D12: Plantio projetado de 2.400 ha (1.400 fundação + 1.000 renovação) sem necessidade de fertilizante calculada; o estoque de fórmulas de plantio cobre 1.397,18 ha pela dose implícita de 600 kg/ha. | E12: Possível necessidade adicional de fórmulas de plantio fora deste balanço — validar escopo e época.
A13: 9 | B13: Alta | C13: Planilha inteira | D13: Não há preços, datas de entrega do 'comprado a receber', prazo de fornecimento, distribuição mensal da demanda nem ritmo de aplicação do fertilizante mineral. | E13: Orçamento, curva real de abastecimento e aderência ao cronograma não podem ser calculados.
A14: 10 | B14: Baixa | C14: LOC. 450ha, seções | D14: Seções numeradas '1. Projeção' e '1. Áreas adubadas' (numeração repetida); grafias 'Fertlizante' e 'Rítmo'. | E14: Apenas apresentação.

Sheet Conferência
A1: Conferência das fórmulas da planilha de origem
A2: Cada fórmula foi refeita em Python (extrair_dados.py) e comparada com o valor gravado pelo Excel.
A4: Aba | B4: Célula | C4: Item | D4: Valor na planilha | E4: Recalculado | F4: Diferença | G4: OK
A5: LOC. 1.000ha | B5: B11 | C5: Dias até limite da localizada | D5: 45 | E5: 45 | F5: =ROUND(E5-D5,6) -> 0 | G5: =IF(ABS(F5)<0.000001,"sim","NÃO") -> sim
A6: LOC. 1.000ha | B6: C11 | C6: Dias até término da safra | D6: 60 | E6: 60 | F6: =ROUND(E6-D6,6) -> 0 | G6: =IF(ABS(F6)<0.000001,"sim","NÃO") -> sim
A7: LOC. 1.000ha | B7: C14 | C7: Área estimada de localizada | D7: 1015.6 | E7: 1015.6 | F7: =ROUND(E7-D7,6) -> 0 | G7: =IF(ABS(F7)<0.000001,"sim","NÃO") -> sim
A8: LOC. 1.000ha | B8: B24 | C8: Total CRV adubado | D8: 14236.43 | E8: 14236.43 | F8: =ROUND(E8-D8,6) -> 0 | G8: =IF(ABS(F8)<0.000001,"sim","NÃO") -> sim
A9: LOC. 1.000ha | B9: E27 | C9: Consumo realizado 46-00-00 | D9: 640.296 | E9: 640.296 | F9: =ROUND(E9-D9,6) -> 0 | G9: =IF(ABS(F9)<0.000001,"sim","NÃO") -> sim
A10: LOC. 1.000ha | B10: E28 | C10: Consumo realizado 16-00-20 | D10: 1063.445 | E10: 1063.445 | F10: =ROUND(E10-D10,6) -> 0 | G10: =IF(ABS(F10)<0.000001,"sim","NÃO") -> sim
A11: LOC. 1.000ha | B11: H36 | C11: Cargill a tratar | D11: 446.63 | E11: 446.63 | F11: =ROUND(E11-D11,6) -> 0 | G11: =IF(ABS(F11)<0.000001,"sim","NÃO") -> sim
A12: LOC. 1.000ha | B12: D38 | C12: CRV áreas à colher | D12: 29726 | E12: 29726 | F12: =ROUND(E12-D12,6) -> 0 | G12: =IF(ABS(F12)<0.000001,"sim","NÃO") -> sim
A13: LOC. 1.000ha | B13: E38 | C13: CRV área de tratos | D13: 28726 | E13: 28726 | F13: =ROUND(E13-D13,6) -> 0 | G13: =IF(ABS(F13)<0.000001,"sim","NÃO") -> sim
A14: LOC. 1.000ha | B14: F38 | C14: Realizado localizada = B22 | D14: 5795.19 | E14: 5795.19 | F14: =ROUND(E14-D14,6) -> 0 | G14: =IF(ABS(F14)<0.000001,"sim","NÃO") -> sim
A15: LOC. 1.000ha | B15: F39 | C15: Realizado mineral = B23 | D15: 8441.24 | E15: 8441.24 | F15: =ROUND(E15-D15,6) -> 0 | G15: =IF(ABS(F15)<0.000001,"sim","NÃO") -> sim
A16: LOC. 1.000ha | B16: F40 | C16: Total realizado CRV | D16: 14236.43 | E16: 14236.43 | F16: =ROUND(E16-D16,6) -> 0 | G16: =IF(ABS(F16)<0.000001,"sim","NÃO") -> sim
... A91: LOC. 450ha | B91: B56 | C91: Sensibilidade 0 dias = cenário B | D91: 2544.32 | E91: 2544.32 | F91: =ROUND(E91-D91,6) -> 0 | G91: =IF(ABS(F91)<0.000001,"sim","NÃO") -> sim
C93: Conferências sem divergência | D93: =COUNTIF(G5:G91,"sim") -> 87 | E93: =COUNTA(G5:G91) -> 87
